mom_xtools/__init__.py
mom_xtools/__main__.py
mom_xtools/_version.py
mom_xtools/cli.py
mom_xtools/mom_budgets.py
mom_xtools/mom_read.py
mom_xtools-0.2.0.dist-info/METADATA
mom_xtools-0.2.0.dist-info/WHEEL
mom_xtools-0.2.0.dist-info/entry_points.txt
mom_xtools-0.2.0.dist-info/top_level.txt
mom_xtools-0.2.0.dist-info/RECORD
