Metadata-Version: 2.1
Name: mom-xtools
Version: 0.2.0
Summary: Collection of xarray based analysis tools for MOM ocean model output
Home-page: https://github.com/jbusecke/mom_xtools
Author: JuliusBusecke
Author-email: jbusecke@princeton.edu
License: UNKNOWN
Keywords: mom_xtools
Platform: UNKNOWN
Classifier: Programming Language :: Python :: 2.7
Classifier: Programming Language :: Python :: 3.6
